maildiscover/__init__.py
maildiscover/autoconfig.py
maildiscover/common.py
maildiscover/dns.py
maildiscover-0.1.0.dist-info/LICENSE
maildiscover-0.1.0.dist-info/METADATA
maildiscover-0.1.0.dist-info/WHEEL
maildiscover-0.1.0.dist-info/top_level.txt
maildiscover-0.1.0.dist-info/RECORD
