Metadata-Version: 2.1
Name: maildiscover
Version: 0.1.0
Summary: Simple library for email connection parameters discovery
Author-email: Leonardo Barcaroli <blallo@autistici.org>
License: This is free and unencumbered software released into the public domain.        
Project-URL: Homepage, https://git.sr.ht/~blallo/maildiscover
Project-URL: Documentation, https://man.sr.ht/~blallo/maildiscover/
Keywords: email,autoconfig,discover,connection
Classifier: License :: CC0 1.0 Universal (CC0 1.0) Public Domain Dedication
Classifier: License :: Public Domain
Requires-Python: >=3.8
License-File: LICENSE
Requires-Dist: requests
Requires-Dist: lxml
Requires-Dist: dnspython
Provides-Extra: dev
Requires-Dist: ipython ; extra == 'dev'
Requires-Dist: black ; extra == 'dev'
Requires-Dist: build ; extra == 'dev'
Requires-Dist: pytest ; extra == 'dev'
Requires-Dist: pytest-integration ; extra == 'dev'
Requires-Dist: pytest-cov ; extra == 'dev'
Requires-Dist: pydoc-markdown ; extra == 'dev'
Requires-Dist: twine ; extra == 'dev'
